mcafee_epo.py
mcafee_epo-1.1.0.dist-info/LICENSE.rst
mcafee_epo-1.1.0.dist-info/METADATA
mcafee_epo-1.1.0.dist-info/WHEEL
mcafee_epo-1.1.0.dist-info/top_level.txt
mcafee_epo-1.1.0.dist-info/RECORD
