Metadata-Version: 2.1
Name: mcafee-epo
Version: 1.1.0
Summary: McAfee ePolicy Orchestrator API client
Home-page: https://github.com/davidism/mcafee-epo
Author: David Lord
Author-email: davidism@gmail.com
License: BSD-3-Clause
Platform: UNKNOWN
Classifier: Development Status :: 5 - Production/Stable
Classifier: Intended Audience :: Developers
Classifier: License :: OSI Approved :: BSD License
Classifier: Operating System :: OS Independent
Classifier: Programming Language :: Python
Classifier: Programming Language :: Python :: 2
Classifier: Programming Language :: Python :: 3
Classifier: Topic :: System :: Systems Administration
Requires-Python: >=2.7, !=3.0.*, !=3.1.*, !=3.2.*, !=3.3.*, !=3.4.*
Requires-Dist: requests
